[
    {
        "keywords": [
            "pantolon","trousers"
        ],
        "name": "pantolon",
        "group":"alt giyim"
    },
    {
        "keywords": [
            "şort","bermuda"
        ],
        "name": "şort",
        "group":"alt giyim"
    },
    {
        "keywords": [
            "eşofman"
        ],
        "name": "eşofman",
        "group":"alt giyim"
    }
    ,   {
        "keywords": [
            "tulum"
        ],
        "name": "tulum",
        "group":"alt giyim"
    } ,   {
        "keywords": [
            "etek","skirt"
        ],
        "name": "etek",
        "group":"alt giyim"
    },   {
        "keywords": [
            "tayt"
        ],
        "name": "tayt",
        "group":"alt giyim"
    },   {
        "keywords": [
            "jogger"
        ],
        "name": "jogger",
        "group":"alt giyim"
    }
]