[
    {
        "keywords": [
            "kaban",
            "mont",
            "palto",
            "manto",
            "trençkot"
        ],
        "words": ["trenchcoat","trenckot"],
        "positives": [
            [
                "kaban",
                "coat"
            ],
            [
                "mont","VAL THORENS","CHAMONIX","Angie","Amber","Blake","Meatpacking","Cherrie","Angelina","Sera","Angie","Lorena","Bank Street","Soho","Malek","RAMİ","BRADLEY","Farrow","Galia","TRIBECA"
            ],
            [
                "palto"
            ],
            [
                "pardösü"
            ],
            [
                "manto"
            ],
            [
                "trençkot",
                "Trench",
                "TRENCKOT",
                "TRENC"
            ]
        ],
        "db": [],
        "negatives": ["network","ceket"],
        "name": "kaban, mont, palto, manto, trençkot",
        "slug": "dis-giyim",
        "exclude": {
       
        }
    }
]